run_command_plugin/__init__.py
run_command_plugin/run_command_plugin.py
run_command_plugin/services/__init__.py
run_command_plugin/services/command_service.py
ambient_run_command_plugin-1.8.0.dist-info/METADATA
ambient_run_command_plugin-1.8.0.dist-info/WHEEL
ambient_run_command_plugin-1.8.0.dist-info/top_level.txt
ambient_run_command_plugin-1.8.0.dist-info/RECORD
