Metadata-Version: 2.4
Name: ambient_run_command_plugin
Version: 1.8.0
Summary: Run command plugin for Ambient platform.
Author-email: Jose Catarino <jose@ambientlabscomputing.com>
License: MIT
Keywords: ambient,plugin,plugin interface
Classifier: Development Status :: 3 - Alpha
Classifier: Intended Audience :: Developers
Classifier: Topic :: Software Development :: Libraries :: Application Frameworks
Classifier: Programming Language :: Python :: 3
Classifier: Programming Language :: Python :: 3.7
Classifier: License :: OSI Approved :: MIT License
Classifier: Operating System :: OS Independent
Requires-Python: >=3.7
Requires-Dist: pluggy<=1.8.0
Requires-Dist: pydantic<=2.7.4
Requires-Dist: ambient_backend_api_client>=3.0.1
